LICENSE.txt
MANIFEST.in
README.md
requirements-dev.txt
requirements-test.txt
setup.py
humilis_dynamodb/__init__.py
humilis_dynamodb/config.py
humilis_dynamodb/humilis_dynamodb.py
humilis_dynamodb/meta.yaml.j2
humilis_dynamodb/outputs.yaml.j2
humilis_dynamodb/plugin.py
humilis_dynamodb/resources.yaml.j2
humilis_dynamodb.egg-info/PKG-INFO
humilis_dynamodb.egg-info/SOURCES.txt
humilis_dynamodb.egg-info/dependency_links.txt
humilis_dynamodb.egg-info/entry_points.txt
humilis_dynamodb.egg-info/not-zip-safe
humilis_dynamodb.egg-info/requires.txt
humilis_dynamodb.egg-info/top_level.txt