Metadata-Version: 1.1
Name: humilis-dynamodb
Version: 0.0.8
Summary: Humilis plug-in to deploy a DynamoDB table
Home-page: https://github.com/humilis/humilis-dynamodb
Author: German Gomez-Herrero, FindHotel BV
Author-email: german@findhotel.net
License: MIT
Platform: UNKNOWN
Classifier: Programming Language :: Python :: 3
